uspto_patent_citation_graph/__init__.py
uspto_patent_citation_graph-0.2109.0.dist-info/LICENSE
uspto_patent_citation_graph-0.2109.0.dist-info/METADATA
uspto_patent_citation_graph-0.2109.0.dist-info/WHEEL
uspto_patent_citation_graph-0.2109.0.dist-info/top_level.txt
uspto_patent_citation_graph-0.2109.0.dist-info/RECORD
