Metadata-Version: 2.1
Name: uspto-patent-citation-graph
Version: 0.2109.0
Summary: graph patent citation USPTO database graphscraper webscraper
Home-page: https://github.com/volfpeter/uspto-patent-citation-graph
Author: Peter Volf
Author-email: do.volfp@gmail.com
License: MIT
Keywords: bootstrap html markup generator utility
Platform: UNKNOWN
Classifier: Development Status :: 5 - Production/Stable
Classifier: Intended Audience :: Developers
Classifier: Intended Audience :: Education
Classifier: Intended Audience :: Science/Research
Classifier: License :: OSI Approved :: MIT License
Classifier: Natural Language :: English
Classifier: Operating System :: OS Independent
Classifier: Programming Language :: Python :: 3 :: Only
Classifier: Programming Language :: Python :: 3.6
Classifier: Programming Language :: Python :: 3.7
Classifier: Programming Language :: Python :: 3.8
Classifier: Topic :: Database
Classifier: Topic :: Education
Classifier: Topic :: Internet :: WWW/HTTP :: Dynamic Content
Classifier: Topic :: Scientific/Engineering
Classifier: Typing :: Typed
Requires-Python: >=3.6
License-File: LICENSE
Requires-Dist: graphscraper (>=0.5)
Requires-Dist: requests (>=2.22)
